odoo/addons/product_category_code_unique/README.rst
odoo/addons/product_category_code_unique/__init__.py
odoo/addons/product_category_code_unique/__manifest__.py
odoo/addons/product_category_code_unique/hooks.py
odoo/addons/product_category_code_unique/data/product_category_sequence.xml
odoo/addons/product_category_code_unique/i18n/it.po
odoo/addons/product_category_code_unique/i18n/product_category_code_unique.pot
odoo/addons/product_category_code_unique/models/__init__.py
odoo/addons/product_category_code_unique/models/product_category.py
odoo/addons/product_category_code_unique/readme/CONTRIBUTORS.md
odoo/addons/product_category_code_unique/readme/DESCRIPTION.md
odoo/addons/product_category_code_unique/static/description/icon.png
odoo/addons/product_category_code_unique/static/description/index.html
odoo/addons/product_category_code_unique/tests/__init__.py
odoo/addons/product_category_code_unique/tests/test_code_unique.py
odoo_addon_product_category_code_unique-17.0.1.0.0.2.dist-info/METADATA
odoo_addon_product_category_code_unique-17.0.1.0.0.2.dist-info/WHEEL
odoo_addon_product_category_code_unique-17.0.1.0.0.2.dist-info/top_level.txt
odoo_addon_product_category_code_unique-17.0.1.0.0.2.dist-info/RECORD
